django_ldap_groups_bsc-0.1.8.4.dist-info/RECORD
django_ldap_groups_bsc-0.1.8.4.dist-info/top_level.txt
django_ldap_groups_bsc-0.1.8.4.dist-info/metadata.json
django_ldap_groups_bsc-0.1.8.4.dist-info/DESCRIPTION.rst
django_ldap_groups_bsc-0.1.8.4.dist-info/WHEEL
django_ldap_groups_bsc-0.1.8.4.dist-info/METADATA
ldap_groups/__init__.py
ldap_groups/views.py
ldap_groups/admin.py
ldap_groups/LICENSE
ldap_groups/settings.py.template
ldap_groups/README
ldap_groups/models.py
ldap_groups/urls.py
ldap_groups/settings.py
ldap_groups/migrations/__init__.py
ldap_groups/migrations/0001_initial.py
ldap_groups/templates/admin/ldap_groups/ldapgroup/change_form.html
ldap_groups/accounts/__init__.py
ldap_groups/accounts/backends.py
